djangocms_pai_ghost_articles/__init__.py
djangocms_pai_ghost_articles/admin.py
djangocms_pai_ghost_articles/apps.py
djangocms_pai_ghost_articles/cms_apps.py
djangocms_pai_ghost_articles/urls.py
djangocms_pai_ghost_articles/views.py
djangocms_pai_ghost_articles/migrations/__init__.py
djangocms_pai_ghost_articles/templates/base_custom_meta.html
djangocms_pai_ghost_articles/templates/ghost/article_detail.html
djangocms_pai_ghost_articles-0.0.2.dist-info/AUTHORS.rst
djangocms_pai_ghost_articles-0.0.2.dist-info/LICENSE.txt
djangocms_pai_ghost_articles-0.0.2.dist-info/METADATA
djangocms_pai_ghost_articles-0.0.2.dist-info/WHEEL
djangocms_pai_ghost_articles-0.0.2.dist-info/top_level.txt
djangocms_pai_ghost_articles-0.0.2.dist-info/RECORD
