Metadata-Version: 2.1
Name: djangocms-pai-ghost-articles
Version: 0.0.2
Summary: Djangocms ghost articles integration.
Home-page: https://bitbucket.org/pai/djangocms-pai-ghost-articles
Author: pai
Author-email: paiuolo@gmail.com
License: mit
Platform: any
Classifier: Development Status :: 4 - Beta
Classifier: Programming Language :: Python
Provides-Extra: testing
Requires-Dist: pytest ; extra == 'testing'
Requires-Dist: pytest-cov ; extra == 'testing'
